miarec_smbfs/__init__.py
miarec_smbfs/_version.txt
miarec_smbfs/file.py
miarec_smbfs/opener.py
miarec_smbfs/smbfs.py
miarec_smbfs/utils.py
miarec_smbfs-2024.1.1.dist-info/COPYING
miarec_smbfs-2024.1.1.dist-info/METADATA
miarec_smbfs-2024.1.1.dist-info/WHEEL
miarec_smbfs-2024.1.1.dist-info/entry_points.txt
miarec_smbfs-2024.1.1.dist-info/top_level.txt
miarec_smbfs-2024.1.1.dist-info/zip-safe
miarec_smbfs-2024.1.1.dist-info/RECORD
